aws_cdk_appsync_transformer/__init__.py
aws_cdk_appsync_transformer/py.typed
aws_cdk_appsync_transformer/_jsii/__init__.py
aws_cdk_appsync_transformer/_jsii/aws-cdk-appsync-transformer@1.63.0-rc.3.jsii.tgz
aws_cdk_appsync_transformer-1.63.0rc3.dist-info/METADATA
aws_cdk_appsync_transformer-1.63.0rc3.dist-info/WHEEL
aws_cdk_appsync_transformer-1.63.0rc3.dist-info/top_level.txt
aws_cdk_appsync_transformer-1.63.0rc3.dist-info/RECORD
