Metadata-Version: 2.1
Name: aws-cdk-appsync-transformer
Version: 1.63.0rc3
Summary: AWS Amplify inspired CDK construct for creating @directive based AppSync APIs
Home-page: https://github.com/kcwinner/appsync-transformer-construct.git
Author: Ken Winner
License: Apache-2.0
Project-URL: Source, https://github.com/kcwinner/appsync-transformer-construct.git
Platform: UNKNOWN
Classifier: Intended Audience :: Developers
Classifier: Operating System :: OS Independent
Classifier: Programming Language :: JavaScript
Classifier: Programming Language :: Python :: 3 :: Only
Classifier: Programming Language :: Python :: 3.6
Classifier: Programming Language :: Python :: 3.7
Classifier: Programming Language :: Python :: 3.8
Classifier: Typing :: Typed
Classifier: Development Status :: 4 - Beta
Classifier: License :: OSI Approved
Requires-Python: >=3.6
Requires-Dist: aws-cdk.aws-appsync (==1.63.0)
Requires-Dist: aws-cdk.aws-cognito (==1.63.0)
Requires-Dist: aws-cdk.aws-dynamodb (==1.63.0)
Requires-Dist: aws-cdk.aws-iam (==1.63.0)
Requires-Dist: aws-cdk.aws-lambda (==1.63.0)
Requires-Dist: aws-cdk.core (==1.63.0)
Requires-Dist: constructs (<4.0.0,>=3.0.4)
Requires-Dist: jsii (<2.0.0,>=1.12.0)
Requires-Dist: publication (>=0.0.3)
